{
    "imt_id": 129987592,
    "nm_id": 163959251,
    "imt_name": "Беспроводные наушники блютуз с шумоподавлением",
    "subj_name": "Наушники",
    "subj_root_name": "Телевизоры и аудиотехника",
    "vendor_code": "ruomi_M28",
    "description": "Наушники беспроводные с микрофоном F9 от бренда Ruomi.\nДоставляем напрямую с завода, что гарантирует самую низкую цену и заводское качество.\nНаушники подходят ко всем современным устройствам с поддержкой функции Bluetooth (для телефона (iPhone, Samsung, Xiaomi и др.), пк и прочих). Сопрягаются с любой операционной системой: IOS, Android, Windows. \n\nКейс оснащен светодиодным LED-дисплеем, который отображает уровень заряда в процентах, чтобы вы точно могли определить когда пора заряжать устройство. А так же вы видите заряд каждого из наушников. (25-100%).\nКрышка кейса надежно фиксируется за счет магнитов, защищая от произвольного открытия кейса в сумке или кармане. Наушники с магнитной зарядкой, благодаря которой они так же надежно зафиксированы внутри зарядного бокса.\nДлительное время автономной работы беспроводных блютуз наушников обеспечивает мощный аккумулятор - 3000 мАч, благодаря этому зарядный бокс наушников выполняет функцию PowerBank, обеспечивая возможность подзарядки вашего смартфона при необходимость. Оснащен двумя портами USB/micro USB.  Кроме этого кейс служит как подставка для телефона. Можно смотреть любимый фильм или сериал удобно расположив свой гаджет на подставке, в то время как вы подзаряжаете его и при этом наслаждаться чистым качественным Hi-FI 9D звуком блютуз наушников. Наушники оснащены современным блютуз модулем - Bluetooth 5.1. \nБеспроводные наушники работают в радиусе 10 метров от устройства к которому подключены, быстрое автоматическое сопряжение. Важно, чтобы в зоне действия блютуз сигнала не было препятствий для сигнала подавляющих его. Это может влиять на качество соединения.\n \nВ комплекте с наушниками идет кабель для зарядки и сменные амбушюры разных размеров для индивидуального подбора комфортного вам размера, исходя из личных особенностей строения уха. Можно использовать как детские беспородные наушники. Отличный вариант на подарок.\nЕмкости аккумулятора хватает для 20 подзарядок наушников, что в сумме дает 100 часов автономной работы. Батарея каждого из наушников тоже отличается повышенной мощностью - 50 мАч, это обеспечивает работу самих наушников до 5 часов без подзарядки. \nНаушники с сенсорным управлением позволят вам совершать основные команды с помощью легкий касаний. Подробнее указано в инструкции.\nВстроенный микрофон в наушниках позволяет использовать их как беспроводную гарнитуру.\nМногофункциональный кейс быстро заряжается от сети, всего 1-2 часа. Внимание! Перед первым использованием зарядите кейс и наушники полностью! F9 TWS - маленькие вакуумные наушники с идеальным качеством звука можно использовать как игровые наушники с микрофоном.\nЗа счет плотного прилегания амбушюр к уху создается эффект шумоподавления, и вы практически не слышите посторонних шумов, а наслаждаетесь любимой музыкой, книгой или фильмом. \n\nБлагодаря отсутствию проводов и сенсорному управлению, такая гарнитура может использоваться во время бега или любого другого вида спорта. Степень защиты от пыли и влаги IPX4, что позволяет использовать наушники даже во время дождя или рядом с водоемами. С завода наушники поставляются уже настроенными на взаимную синхронизацию. Доставать наушники из кейса следует одновременно, а уже потом помещать их в уши. Это необходимо для автоматической синхронизации наушников между собой. Если один из наушников подключился к мобильному устройству прежде чем синхронизироваться со вторым - второй работать не будет. Это принцип автономной работы техники. Они являются полноценными устройствами сами по себе. Для подключения второго, в таком случае, необходимо выполнить синхронизацию между наушниками повторно. Пошаговые действия будут описаны в русскоязычном руководстве пользователя, которое идет в комплекте со всеми нашими наушниками. \n\nВажно! Беспроводные наушники работают устройствами с версией Bluetooth 5.0 и выше, при более ранней версии Bluetooth, наушники могут работать некорректно ( могут отключаться, прерывается звук, работает только один наушник).",
    "grouped_options": [
        {
            "group_name": "Питание",
            "options": [
                {
                    "name": "Время зарядки",
                    "value": "1-2 часа"
                },
                {
                    "name": "Емкость аккумулятора",
                    "value": "2000 мА*ч"
                },
                {
                    "name": "Время работы от аккумулятора",
                    "value": "4-6 часов в режиме музыки и разговора"
                }
            ]
        },
        {
            "group_name": "Дополнительная информация",
            "options": [
                {
                    "name": "Длина кабеля (м)",
                    "value": "0.25 м"
                },
                {
                    "name": "Возрастная группа",
                    "value": "для всех возрастов"
                },
                {
                    "name": "Тип соединения",
                    "value": "беспроводные; без проводные"
                },
                {
                    "name": "Тип акустического оформления",
                    "value": "стерео; hi-fi; басы"
                },
                {
                    "name": "Тип крепления наушников",
                    "value": "вакуумные; в ушной раковине; внутриканальные"
                },
                {
                    "name": "Назначение товара",
                    "value": "автоаксессуары; наушники и гарнитуры"
                },
                {
                    "name": "Доп. опции наушников",
                    "value": "tws наушники детские с микрофоном; пауэрбанк PowerBank; подставка для мобильного телефона"
                },
                {
                    "name": "Страна производства",
                    "value": "Китай"
                },
                {
                    "name": "Совместимость",
                    "value": "для телефона смартфона; для айфона и для андроида; для пк для компьютера тв"
                }
            ]
        },
        {
            "group_name": "Общие характеристики",
            "options": [
                {
                    "name": "Степень пылевлагозащиты",
                    "value": "IPX4; влагозащита от брызг воды"
                },
                {
                    "name": "Модель",
                    "value": "беспроводные наушники ф-9; гарнитура с микрофоном"
                },
                {
                    "name": "Вид наушников",
                    "value": "вакуумные; игровые; беспроводные"
                },
                {
                    "name": "Тип подключения",
                    "value": "беспроводные"
                }
            ]
        },
        {
            "group_name": "Технические особенности",
            "options": [
                {
                    "name": "Радиус беспроводной связи",
                    "value": "10-15 м"
                }
            ]
        },
        {
            "group_name": "Материалы",
            "options": [
                {
                    "name": "Материал корпуса",
                    "value": "abs-пластик"
                }
            ]
        },
        {
            "group_name": "Другие функции",
            "options": [
                {
                    "name": "Хрупкость",
                    "value": "да"
                }
            ]
        },
        {
            "group_name": "Связь",
            "options": [
                {
                    "name": "Беспроводные интерфейсы",
                    "value": "Bluetooth; наушники с блютус"
                }
            ]
        },
        {
            "group_name": "Интерфейсы и разъемы",
            "options": [
                {
                    "name": "Разъем подключения наушников",
                    "value": "без проводные; USB/micro USB порты"
                }
            ]
        },
        {
            "group_name": "Габариты",
            "options": [
                {
                    "name": "Длина упаковки",
                    "value": "27 см"
                },
                {
                    "name": "Высота упаковки",
                    "value": "5 см"
                },
                {
                    "name": "Ширина упаковки",
                    "value": "17 см"
                }
            ]
        }
    ],
    "options": [
        {
            "name": "Время зарядки",
            "value": "1-2 часа"
        },
        {
            "name": "Длина кабеля (м)",
            "value": "0.25 м"
        },
        {
            "name": "Возрастная группа",
            "value": "для всех возрастов"
        },
        {
            "name": "Степень пылевлагозащиты",
            "value": "IPX4; влагозащита от брызг воды"
        },
        {
            "name": "Тип соединения",
            "value": "беспроводные; без проводные"
        },
        {
            "name": "Радиус беспроводной связи",
            "value": "10-15 м"
        },
        {
            "name": "Тип акустического оформления",
            "value": "стерео; hi-fi; басы"
        },
        {
            "name": "Тип крепления наушников",
            "value": "вакуумные; в ушной раковине; внутриканальные"
        },
        {
            "name": "Емкость аккумулятора",
            "value": "2000 мА*ч"
        },
        {
            "name": "Материал корпуса",
            "value": "abs-пластик"
        },
        {
            "name": "Время работы от аккумулятора",
            "value": "4-6 часов в режиме музыки и разговора"
        },
        {
            "name": "Хрупкость",
            "value": "да"
        },
        {
            "name": "Назначение товара",
            "value": "автоаксессуары; наушники и гарнитуры"
        },
        {
            "name": "Доп. опции наушников",
            "value": "tws наушники детские с микрофоном; пауэрбанк PowerBank; подставка для мобильного телефона"
        },
        {
            "name": "Модель",
            "value": "беспроводные наушники ф-9; гарнитура с микрофоном"
        },
        {
            "name": "Страна производства",
            "value": "Китай"
        },
        {
            "name": "Беспроводные интерфейсы",
            "value": "Bluetooth; наушники с блютус"
        },
        {
            "name": "Вид наушников",
            "value": "вакуумные; игровые; беспроводные"
        },
        {
            "name": "Совместимость",
            "value": "для телефона смартфона; для айфона и для андроида; для пк для компьютера тв"
        },
        {
            "name": "Разъем подключения наушников",
            "value": "без проводные; USB/micro USB порты"
        },
        {
            "name": "Тип подключения",
            "value": "беспроводные"
        },
        {
            "name": "Длина упаковки",
            "value": "27 см"
        },
        {
            "name": "Высота упаковки",
            "value": "5 см"
        },
        {
            "name": "Ширина упаковки",
            "value": "17 см"
        }
    ],
    "certificate": {
        "verified": true
    },
    "nm_colors_names": "черный",
    "colors": [
        159779336,
        159779335,
        153112738,
        163959251,
        157139415,
        163906913,
        164847094
    ],
    "contents": "наушники беспроводные; кейс для подзарядки",
    "full_colors": [
        {
            "nm_id": 159779336
        },
        {
            "nm_id": 159779335
        },
        {
            "nm_id": 153112738
        },
        {
            "nm_id": 163959251
        },
        {
            "nm_id": 157139415
        },
        {
            "nm_id": 163906913
        },
        {
            "nm_id": 164847094
        }
    ],
    "selling": {
        "no_return_map": 4351,
        "brand_name": "RUOMI",
        "supplier_id": 1189949
    },
    "media": {
        "photo_count": 6
    },
    "data": {
        "subject_id": 593,
        "subject_root_id": 6260,
        "chrt_ids": [
            273199816
        ],
        "tech_size": "0",
        "skus": [
            "2037949005733"
        ]
    }
}